pygmm/__init__.py
pygmm/_version.py
pygmm/abrahamson_bhasin_2020.py
pygmm/abrahamson_gregor_addo_2016.py
pygmm/abrahamson_silva_1996.py
pygmm/abrahamson_silva_kamai_2014.py
pygmm/afshari_stewart_2016.py
pygmm/akkar_sandikkaya_bommer_2014.py
pygmm/atkinson_boore_2006.py
pygmm/baker_jayaram_2008.py
pygmm/bayless_abrahamson_2018.py
pygmm/bayless_abrahamson_2019.py
pygmm/boore_stewart_seyhan_atkinson_2014.py
pygmm/campbell_2003.py
pygmm/campbell_bozorgnia_2014.py
pygmm/chiou_youngs_2014.py
pygmm/coppersmith_bommer_2014.py
pygmm/derras_bard_cotton_2014.py
pygmm/gulerce_abrahamson_2011.py
pygmm/hermkes_kuehn_riggelsen_2014.py
pygmm/idriss_2014.py
pygmm/kempton_stewart_2006.py
pygmm/kishida_2017.py
pygmm/model.py
pygmm/pezeshk_zandieh_tavakoli_2011.py
pygmm/pinilla_ramos_et_al_2023.py
pygmm/pinilla_ramos_et_al_2024.py
pygmm/stafford_2017.py
pygmm/tavakoli_pezeshk_2005.py
pygmm/tools.py
pygmm/types.py
pygmm/data/abrahamson_gregor_addo_2016.csv
pygmm/data/abrahamson_silva_kamai_2014.csv
pygmm/data/akkar-sandikkaya-bommer-2014-dist_epi.csv
pygmm/data/akkar-sandikkaya-bommer-2014-dist_hyp.csv
pygmm/data/akkar-sandikkaya-bommer-2014-dist_jb.csv
pygmm/data/atkinson_boore_2006-bc.csv
pygmm/data/atkinson_boore_2006-rock.csv
pygmm/data/atkinson_boore_2006-sf.csv
pygmm/data/atkinson_boore_2006-site.csv
pygmm/data/bayless_abrahamson_2018.csv
pygmm/data/bayless_abrahamson_2019.csv
pygmm/data/boore_stewart_seyhan_atkinson-2014.csv
pygmm/data/campbell_2003.csv
pygmm/data/campbell_bozorgnia_2014.csv
pygmm/data/chiou_youngs_2014.csv
pygmm/data/coppersmith_bommer_2014.csv
pygmm/data/derras_bard_cotton_2014.json
pygmm/data/gulerce_abrahamson_2011-coefficients.csv
pygmm/data/gulerce_abrahamson_2011-correl-between.csv
pygmm/data/gulerce_abrahamson_2011-correl-within.csv
pygmm/data/hermkes_kuehn_riggelsen_2014.npz
pygmm/data/idriss_2014-large.csv
pygmm/data/idriss_2014-small.csv
pygmm/data/pezeshk_zandieh_tavakoli_2011.csv
pygmm/data/stafford_2017.json
pygmm/data/tavakoli_pezeshk_2005.csv
pygmm-0.8.0.dist-info/licenses/AUTHORS.md
pygmm-0.8.0.dist-info/licenses/LICENSE
pygmm-0.8.0.dist-info/METADATA
pygmm-0.8.0.dist-info/WHEEL
pygmm-0.8.0.dist-info/top_level.txt
pygmm-0.8.0.dist-info/RECORD
