Metadata-Version: 2.4
Name: pyGMM
Version: 0.8.0
Summary: Ground motion models implemented in Python.
Author-email: Albert Kottke <albert.kottke@gmail.com>
License: MIT
Project-URL: Homepage, https://github.com/arkottke/pygmm
Project-URL: Documentation, https://pygmm.readthedocs.io
Requires-Python: >=3.10
License-File: LICENSE
License-File: AUTHORS.md
Requires-Dist: matplotlib
Requires-Dist: numpy
Requires-Dist: pandas
Requires-Dist: scipy
Provides-Extra: test
Requires-Dist: coverage[toml]; extra == "test"
Requires-Dist: pytest; extra == "test"
Requires-Dist: pytest-cov; extra == "test"
Requires-Dist: pandas; extra == "test"
Provides-Extra: docs
Requires-Dist: sphinx; extra == "docs"
Requires-Dist: furo; extra == "docs"
Requires-Dist: sphinx-copybutton; extra == "docs"
Requires-Dist: sphinx-design; extra == "docs"
Requires-Dist: sphinxcontrib-bibtex; extra == "docs"
Requires-Dist: sphinxext-opengraph; extra == "docs"
Requires-Dist: sphinx-autobuild; extra == "docs"
Requires-Dist: myst-parser; extra == "docs"
Requires-Dist: nbsphinx; extra == "docs"
Requires-Dist: ipython; extra == "docs"
Requires-Dist: linkify-it-py; extra == "docs"
Requires-Dist: lxml[html_clean]; extra == "docs"
Provides-Extra: style
Requires-Dist: black[colorama,jupyter]; extra == "style"
Requires-Dist: ruff; extra == "style"
Dynamic: license-file
